cpd-alp/__init__.py
cpd-alp/affine_registration.py
cpd-alp/deformable_registration.py
cpd-alp/emregistration.py
cpd-alp/rigid_registration.py
cpd-alp/utility.py
cpdalp/__init__.py
cpdalp/affine_registration.py
cpdalp/deformable_registration.py
cpdalp/emregistration.py
cpdalp/rigid_registration.py
cpdalp/utility.py
cpdalp-1.2.0.dist-info/LICENSE
cpdalp-1.2.0.dist-info/METADATA
cpdalp-1.2.0.dist-info/WHEEL
cpdalp-1.2.0.dist-info/top_level.txt
cpdalp-1.2.0.dist-info/RECORD
