Metadata-Version: 2.1
Name: cpdalp
Version: 1.2.0
Summary: ALPACA-centered Pure Numpy Implementation of the Coherent Point Drift Algorithm
Home-page: https://github.com/agporto/pycpd
Author: Arthur Porto
Author-email: agporto@gmail.com
License: MIT
Keywords: image processing,point cloud,registration,mesh,surface
Platform: UNKNOWN
Classifier: Development Status :: 3 - Alpha
Classifier: License :: OSI Approved :: MIT License
Classifier: Programming Language :: Python :: 2.7
Classifier: Programming Language :: Python :: 3.4
Classifier: Programming Language :: Python :: 3.5
Classifier: Programming Language :: Python :: 3.6
Classifier: Topic :: Scientific/Engineering
License-File: LICENSE
Requires-Dist: numpy
